TuringRobots/TuringRobots.py
TuringRobots/__init__.py
TuringRobots/__version__.py
TuringRobots/req.py
TuringRobots-1.2.11.dist-info/LICENSE
TuringRobots-1.2.11.dist-info/METADATA
TuringRobots-1.2.11.dist-info/WHEEL
TuringRobots-1.2.11.dist-info/top_level.txt
TuringRobots-1.2.11.dist-info/RECORD
