Metadata-Version: 2.1
Name: TuringRobots
Version: 1.2.11
Summary: Simple dialogue test Turing robot.
Home-page: https://github.com/AndersonHJB/TuringRobots
Author: Bornforthis
Author-email: bornforthis@bornforthis.cn
License: MIT
Classifier: License :: OSI Approved :: MIT License
Classifier: Programming Language :: Python
Classifier: Programming Language :: Python :: 3
Classifier: Programming Language :: Python :: 3.6
Classifier: Programming Language :: Python :: Implementation :: CPython
Classifier: Programming Language :: Python :: Implementation :: PyPy
Requires-Python: >=3.6.0
License-File: LICENSE
